phiarchive.py
phiarchive-2.0.0.dist-info/licenses/LICENSE
phiarchive-2.0.0.dist-info/METADATA
phiarchive-2.0.0.dist-info/WHEEL
phiarchive-2.0.0.dist-info/top_level.txt
phiarchive-2.0.0.dist-info/RECORD
