Metadata-Version: 2.4
Name: phiarchive
Version: 2.0.0
Summary: Phigros Cloud record and Local record tool Made by Teinxiction
Author-email: Teinxiction <3136695361@qq.com>
License: MIT
Project-URL: Homepage, https://github.com/Teinxiction/PhiArchive
Project-URL: Bug Tracker, https://github.com/Teinxiction/PhiArchive/issues
Keywords: phigros,game,archive,crypto,decrypt,cloud-save
Classifier: Programming Language :: Python :: 3
Classifier: License :: OSI Approved :: MIT License
Classifier: Operating System :: OS Independent
Classifier: Development Status :: 4 - Beta
Classifier: Intended Audience :: Developers
Classifier: Topic :: Security :: Cryptography
Classifier: Topic :: Software Development :: Libraries :: Python Modules
License-File: LICENSE
Requires-Dist: requests>=2.28.0
Requires-Dist: pycryptodome>=3.17.0
Dynamic: license-file
